jimg_int/__init__.py
jimg_int/config.py
jimg_int/intensity.py
jimg_int/utils.py
jimg_int-0.1.0.dist-info/licenses/license.txt
jimg_int-0.1.0.dist-info/METADATA
jimg_int-0.1.0.dist-info/WHEEL
jimg_int-0.1.0.dist-info/RECORD
