Metadata-Version: 2.4
Name: jimg_int
Version: 0.1.0
Summary: 
License-File: license.txt
Author: Jakub Kubis - JBS
Author-email: jbiosystem@gmail.com
Requires-Python: >=3.12,<3.13
Classifier: Programming Language :: Python :: 3
Classifier: Programming Language :: Python :: 3.12
Requires-Dist: gdown (>=5.2.0,<6.0.0)
Requires-Dist: matplotlib (<3.10.0)
Requires-Dist: numpy (==1.26.0)
Requires-Dist: opencv-python
Requires-Dist: openpyxl (>=3.1.5,<4.0.0)
Requires-Dist: pandas
Requires-Dist: pingouin
Requires-Dist: plotly
Requires-Dist: scikit-image
Requires-Dist: scipy
Requires-Dist: tensorflow (>=2.20.0,<3.0.0)
Requires-Dist: tqdm
